CHANGES.md
MANIFEST.in
README.md
VERSION
nge.timings.sh
nge_mangle.py
setup.py
bin/radical-nge-service.py
bin/radical-nge-service.sh
examples/00_nge.py
examples/00_rp.py
examples/01_nge.py
examples/02_nge.py
src/radical/__init__.py
src/radical.nge.egg-info/PKG-INFO
src/radical.nge.egg-info/SOURCES.txt
src/radical.nge.egg-info/dependency_links.txt
src/radical.nge.egg-info/namespace_packages.txt
src/radical.nge.egg-info/not-zip-safe
src/radical.nge.egg-info/requires.txt
src/radical.nge.egg-info/top_level.txt
src/radical/nge/SDIST
src/radical/nge/VERSION
src/radical/nge/__init__.py
src/radical/nge/nge_rp.py
src/radical/nge/nge_rs.py
src/radical/nge/policies/__init__.py
src/radical/nge/policies/default.json
src/radical/nge/utils/__init__.py
src/radical/nge/utils/misc.py